pma/__init__.py
pma/cli.py
pma/integrations/__init__.py
pma/integrations/linear.py
pma/main.py
pma/mcp_servers/__init__.py
pma/mcp_servers/linear/__init__.py
pma/mcp_servers/linear/issues.py
pma/mcp_servers/linear/mcp_server.py
pma/mcp_servers/linear/team.py
pma/test_cli.py
pma/utils/constants.py
pma/utils/print.py
pma/utils/prompts.py
pma/utils/singleton.py
clea_pma-0.2.1.dist-info/METADATA
clea_pma-0.2.1.dist-info/WHEEL
clea_pma-0.2.1.dist-info/entry_points.txt
clea_pma-0.2.1.dist-info/RECORD
